comfy_kitchen/__init__.py
comfy_kitchen/constraints.py
comfy_kitchen/exceptions.py
comfy_kitchen/float_utils.py
comfy_kitchen/registry.py
comfy_kitchen/backends/cuda/__init__.py
comfy_kitchen/backends/cuda/cublaslt_runtime.h
comfy_kitchen/backends/cuda/dtype_dispatch.cuh
comfy_kitchen/backends/cuda/float_utils.cuh
comfy_kitchen/backends/cuda/utils.cuh
comfy_kitchen/backends/eager/__init__.py
comfy_kitchen/backends/eager/quantization.py
comfy_kitchen/backends/eager/rope.py
comfy_kitchen/backends/triton/__init__.py
comfy_kitchen/backends/triton/quantization.py
comfy_kitchen/backends/triton/rope.py
comfy_kitchen/tensor/__init__.py
comfy_kitchen/tensor/base.py
comfy_kitchen/tensor/fp8.py
comfy_kitchen/tensor/nvfp4.py
comfy_kitchen-0.2.7.dist-info/licenses/LICENSE
comfy_kitchen-0.2.7.dist-info/licenses/NOTICE
comfy_kitchen-0.2.7.dist-info/METADATA
comfy_kitchen-0.2.7.dist-info/WHEEL
comfy_kitchen-0.2.7.dist-info/top_level.txt
comfy_kitchen-0.2.7.dist-info/RECORD
