Metadata-Version: 2.4
Name: comfy-kitchen
Version: 0.2.7
Summary: Fast Kernel Library for ComfyUI with multiple compute backends
License: Apache-2.0
Project-URL: Homepage, https://github.com/Comfy-Org/comfy-kitchen
Keywords: pytorch,cuda,quantization,kernels,diffusion
Classifier: Development Status :: 3 - Alpha
Classifier: Programming Language :: Python :: 3
Classifier: Programming Language :: C++
Classifier: License :: OSI Approved :: Apache Software License
Requires-Python: >=3.10
License-File: LICENSE
License-File: NOTICE
Provides-Extra: cublas
Requires-Dist: nvidia-cublas>=13.0.0; extra == "cublas"
Provides-Extra: dev
Requires-Dist: pytest>=7.0.0; extra == "dev"
Requires-Dist: pytest-benchmark>=4.0.0; extra == "dev"
Requires-Dist: ruff>=0.1.0; extra == "dev"
Provides-Extra: build
Requires-Dist: nanobind>=2.0.0; extra == "build"
Dynamic: license-file
